[
    {
        "identifier": "part1item1",
        "character_count": 648834
    },
    {
        "identifier": "part1item2",
        "character_count": 256104
    },
    {
        "identifier": "part1item3",
        "character_count": 4957
    },
    {
        "identifier": "part1item4",
        "character_count": 5916
    },
    {
        "identifier": "part2item1",
        "character_count": 1482
    },
    {
        "identifier": "part2item1a",
        "character_count": 287905
    },
    {
        "identifier": "part2item2",
        "character_count": 14547
    },
    {
        "identifier": "part2item3",
        "character_count": 557
    },
    {
        "identifier": "part2item4",
        "character_count": 549
    },
    {
        "identifier": "part2item5",
        "character_count": 1052
    },
    {
        "identifier": "part2item6",
        "character_count": 28165
    }
]